ducklingaling/__init__.py
ducklingaling/_pandas.py
ducklingaling/aio.py
ducklingaling/connection.py
ducklingaling/cursor.py
ducklingaling/exceptions.py
ducklingaling/pool.py
ducklingaling/py.typed
ducklingaling/types.py
ducklingaling/_async/__init__.py
ducklingaling-0.1.0.dist-info/METADATA
ducklingaling-0.1.0.dist-info/WHEEL
ducklingaling-0.1.0.dist-info/RECORD
