Metadata-Version: 2.4
Name: ducklingaling
Version: 0.1.0
Summary: DB-API 2.0 compliant Python client library for DuckDBLayer
Author: DuckDBLayer Team
License-Expression: MIT
Keywords: async,database,db-api,duckdb,postgresql
Classifier: Development Status :: 3 - Alpha
Classifier: Intended Audience :: Developers
Classifier: License :: OSI Approved :: MIT License
Classifier: Operating System :: OS Independent
Classifier: Programming Language :: Python :: 3
Classifier: Programming Language :: Python :: 3.9
Classifier: Programming Language :: Python :: 3.10
Classifier: Programming Language :: Python :: 3.11
Classifier: Programming Language :: Python :: 3.12
Classifier: Programming Language :: Python :: 3.13
Classifier: Topic :: Database
Classifier: Topic :: Database :: Front-Ends
Classifier: Typing :: Typed
Requires-Python: >=3.9
Requires-Dist: psycopg2-binary>=2.9.0
Provides-Extra: all
Requires-Dist: asyncpg>=0.29.0; extra == 'all'
Requires-Dist: pandas>=1.5.0; extra == 'all'
Provides-Extra: async
Requires-Dist: asyncpg>=0.29.0; extra == 'async'
Provides-Extra: dev
Requires-Dist: asyncpg>=0.29.0; extra == 'dev'
Requires-Dist: mypy>=1.0.0; extra == 'dev'
Requires-Dist: pandas>=1.5.0; extra == 'dev'
Requires-Dist: pytest-asyncio>=0.21.0; extra == 'dev'
Requires-Dist: pytest-cov>=4.0.0; extra == 'dev'
Requires-Dist: pytest>=7.0.0; extra == 'dev'
Requires-Dist: ruff>=0.1.0; extra == 'dev'
Provides-Extra: pandas
Requires-Dist: pandas>=1.5.0; extra == 'pandas'
